auto_gpt_plugin_template/__init__.py
auto_gpt_plugin_template-0.0.3.dist-info/METADATA
auto_gpt_plugin_template-0.0.3.dist-info/WHEEL
auto_gpt_plugin_template-0.0.3.dist-info/licenses/LICENSE
auto_gpt_plugin_template-0.0.3.dist-info/RECORD
