Metadata-Version: 2.1
Name: auto_gpt_plugin_template
Version: 0.0.3
Summary: The template plugin for Auto-GPT.
Project-URL: Homepage, https://github.com/Significant-Gravitas/Auto-GPT
Project-URL: Bug Tracker, https://github.com/Significant-Gravitas/Auto-GPT
Author-email: Torantulino <support@agpt.co>
License-File: LICENSE
Classifier: License :: OSI Approved :: MIT License
Classifier: Operating System :: OS Independent
Classifier: Programming Language :: Python :: 3
Requires-Python: >=3.8
Requires-Dist: abstract-singleton
